{"mean":{"confidence_interval":{"confidence_level":0.95,"lower_bound":18381639.829166666,"upper_bound":18658332.218333326},"point_estimate":18516078.153333332,"standard_error":70584.70016949101},"median":{"confidence_interval":{"confidence_level":0.95,"lower_bound":18340690.5,"upper_bound":18616681.333333332},"point_estimate":18514448.166666664,"standard_error":81205.23919126463},"median_abs_dev":{"confidence_interval":{"confidence_level":0.95,"lower_bound":421168.1049227659,"upper_bound":714316.4387508489},"point_estimate":553651.5088707218,"standard_error":76529.2499876254},"slope":null,"std_dev":{"confidence_interval":{"confidence_level":0.95,"lower_bound":533219.7335219524,"upper_bound":874890.987681405},"point_estimate":705004.5947037123,"standard_error":88315.39064156302}}