{"mean":{"confidence_interval":{"confidence_level":0.95,"lower_bound":9472.809457923051,"upper_bound":9560.110054892955},"point_estimate":9506.473312946437,"standard_error":23.272478484310923},"median":{"confidence_interval":{"confidence_level":0.95,"lower_bound":9456.597623966944,"upper_bound":9484.532467532468},"point_estimate":9471.116430700447,"standard_error":8.257902475220112},"median_abs_dev":{"confidence_interval":{"confidence_level":0.95,"lower_bound":39.157700570922415,"upper_bound":63.274054402451085},"point_estimate":52.70851344170063,"standard_error":6.094222761446718},"slope":{"confidence_interval":{"confidence_level":0.95,"lower_bound":9489.62948532387,"upper_bound":9700.257049791728},"point_estimate":9562.372718137485,"standard_error":60.81769732276629},"std_dev":{"confidence_interval":{"confidence_level":0.95,"lower_bound":48.97328195537339,"upper_bound":385.9578318220087},"point_estimate":233.59700908796083,"standard_error":105.19891963746599}}