{"mean":{"confidence_interval":{"confidence_level":0.95,"lower_bound":154380.30669803798,"upper_bound":157991.4685381915},"point_estimate":156145.3468512282,"standard_error":921.9153467970608},"median":{"confidence_interval":{"confidence_level":0.95,"lower_bound":153084.35,"upper_bound":156342.73556995287},"point_estimate":154587.61279557587,"standard_error":936.2974934298848},"median_abs_dev":{"confidence_interval":{"confidence_level":0.95,"lower_bound":6319.132510447676,"upper_bound":10975.839215353491},"point_estimate":8971.517562069512,"standard_error":1158.6943874546264},"slope":{"confidence_interval":{"confidence_level":0.95,"lower_bound":154597.19775050084,"upper_bound":159145.8858590842},"point_estimate":156905.2929422196,"standard_error":1159.6755017885828},"std_dev":{"confidence_interval":{"confidence_level":0.95,"lower_bound":7719.259533099689,"upper_bound":10715.964583435458},"point_estimate":9287.818536937424,"standard_error":765.3392968640076}}