{"mean":{"confidence_interval":{"confidence_level":0.95,"lower_bound":19698984.358833335,"upper_bound":19732226.174249995},"point_estimate":19712818.03666667,"standard_error":8648.861203411463},"median":{"confidence_interval":{"confidence_level":0.95,"lower_bound":19687564.0,"upper_bound":19713051.333333332},"point_estimate":19696974.5,"standard_error":7001.146324890729},"median_abs_dev":{"confidence_interval":{"confidence_level":0.95,"lower_bound":31283.35364461037,"upper_bound":50498.590603474484},"point_estimate":42576.07054412549,"standard_error":4813.136740020861},"slope":null,"std_dev":{"confidence_interval":{"confidence_level":0.95,"lower_bound":35773.85425742125,"upper_bound":137809.82258449544},"point_estimate":86811.25251709454,"standard_error":32920.318923954765}}