{"mean":{"confidence_interval":{"confidence_level":0.95,"lower_bound":6484983.75084375,"upper_bound":6547747.28375},"point_estimate":6509724.73625,"standard_error":16565.24045069505},"median":{"confidence_interval":{"confidence_level":0.95,"lower_bound":6465878.875,"upper_bound":6485762.125},"point_estimate":6478046.1875,"standard_error":5395.6823314273115},"median_abs_dev":{"confidence_interval":{"confidence_level":0.95,"lower_bound":24954.659444466233,"upper_bound":42893.841138482094},"point_estimate":36624.48182478547,"standard_error":4480.972022139321},"slope":null,"std_dev":{"confidence_interval":{"confidence_level":0.95,"lower_bound":50489.11969525325,"upper_bound":271429.25178136054},"point_estimate":166243.19207303663,"standard_error":71477.55395237688}}