{"mean":{"confidence_interval":{"confidence_level":0.95,"lower_bound":8512760.530166663,"upper_bound":8543677.442291666},"point_estimate":8526865.381666664,"standard_error":7912.240277208499},"median":{"confidence_interval":{"confidence_level":0.95,"lower_bound":8507140.583333332,"upper_bound":8538706.833333334},"point_estimate":8529981.0,"standard_error":8213.792124217278},"median_abs_dev":{"confidence_interval":{"confidence_level":0.95,"lower_bound":45712.63433843851,"upper_bound":81123.44129227044},"point_estimate":61872.85050153778,"standard_error":9755.832250062682},"slope":null,"std_dev":{"confidence_interval":{"confidence_level":0.95,"lower_bound":50210.473820288265,"upper_bound":114448.89680788829},"point_estimate":79489.15014514967,"standard_error":19648.824887593426}}