{"mean":{"confidence_interval":{"confidence_level":0.95,"lower_bound":5695402.201111112,"upper_bound":5707663.689583332},"point_estimate":5700934.855555555,"standard_error":3142.7618998018725},"median":{"confidence_interval":{"confidence_level":0.95,"lower_bound":5690506.166666666,"upper_bound":5698490.333333333},"point_estimate":5694469.0,"standard_error":2203.5124777955602},"median_abs_dev":{"confidence_interval":{"confidence_level":0.95,"lower_bound":11872.166389227374,"upper_bound":20020.618211229335},"point_estimate":17839.219449957367,"standard_error":2027.6033517951557},"slope":null,"std_dev":{"confidence_interval":{"confidence_level":0.95,"lower_bound":17043.6037822922,"upper_bound":45830.78979379389},"point_estimate":31577.78311317641,"standard_error":7810.420503632034}}