{"mean":{"confidence_interval":{"confidence_level":0.95,"lower_bound":206445170.0755,"upper_bound":209389418.74},"point_estimate":207888650.35,"standard_error":752851.4910840145},"median":{"confidence_interval":{"confidence_level":0.95,"lower_bound":202394835.5,"upper_bound":209271113.0},"point_estimate":202934614.5,"standard_error":2234411.1448109164},"median_abs_dev":{"confidence_interval":{"confidence_level":0.95,"lower_bound":1697815.6684577465,"upper_bound":10547990.129935741},"point_estimate":3213202.5992542505,"standard_error":2734149.3928996483},"slope":null,"std_dev":{"confidence_interval":{"confidence_level":0.95,"lower_bound":6394135.804862945,"upper_bound":8722771.26454686},"point_estimate":7577889.466405139,"standard_error":595793.6070448403}}