{"mean":{"confidence_interval":{"confidence_level":0.95,"lower_bound":107990826.98,"upper_bound":108460676.90025},"point_estimate":108217968.96,"standard_error":119713.60802605035},"median":{"confidence_interval":{"confidence_level":0.95,"lower_bound":108204225.0,"upper_bound":108511459.0},"point_estimate":108456528.5,"standard_error":84061.07855818052},"median_abs_dev":{"confidence_interval":{"confidence_level":0.95,"lower_bound":358506.75833523273,"upper_bound":1272482.8104814135},"point_estimate":557878.6484956741,"standard_error":265655.465611074},"slope":null,"std_dev":{"confidence_interval":{"confidence_level":0.95,"lower_bound":939888.1551899235,"upper_bound":1440596.6262044068},"point_estimate":1202303.425058782,"standard_error":128288.88388793383}}