{"mean":{"confidence_interval":{"confidence_level":0.95,"lower_bound":78696.59017918803,"upper_bound":80474.91680868194},"point_estimate":79668.56108049692,"standard_error":453.9201822008393},"median":{"confidence_interval":{"confidence_level":0.95,"lower_bound":79295.15180652682,"upper_bound":79776.77151310229},"point_estimate":79489.70337995338,"standard_error":137.06542029010987},"median_abs_dev":{"confidence_interval":{"confidence_level":0.95,"lower_bound":781.2524513744688,"upper_bound":2099.1742324050574},"point_estimate":1195.284211257075,"standard_error":384.609137907388},"slope":{"confidence_interval":{"confidence_level":0.95,"lower_bound":80282.46634836159,"upper_bound":81500.02077386426},"point_estimate":80860.12701549374,"standard_error":310.92312113981836},"std_dev":{"confidence_interval":{"confidence_level":0.95,"lower_bound":2521.8289225604544,"upper_bound":6664.5166591738425},"point_estimate":4549.086755912958,"standard_error":1158.0477846572194}}