{"mean":{"confidence_interval":{"confidence_level":0.95,"lower_bound":79158.83943993917,"upper_bound":81011.21338059758},"point_estimate":80155.46379199921,"standard_error":474.4940925807865},"median":{"confidence_interval":{"confidence_level":0.95,"lower_bound":79371.57507318264,"upper_bound":80411.12728937728},"point_estimate":79700.57921359038,"standard_error":269.60097076539967},"median_abs_dev":{"confidence_interval":{"confidence_level":0.95,"lower_bound":1237.8896696023162,"upper_bound":2624.948118312283},"point_estimate":1669.8821686709691,"standard_error":371.47047043178145},"slope":{"confidence_interval":{"confidence_level":0.95,"lower_bound":80905.42578703976,"upper_bound":82543.29542014131},"point_estimate":81681.86025940366,"standard_error":419.3823185433694},"std_dev":{"confidence_interval":{"confidence_level":0.95,"lower_bound":2941.4421577830585,"upper_bound":6775.170358539884},"point_estimate":4774.153417043158,"standard_error":1067.2361839997484}}