{"mean":{"confidence_interval":{"confidence_level":0.95,"lower_bound":78151.3287490986,"upper_bound":79910.37899366528},"point_estimate":79122.58353793473,"standard_error":450.178541302997},"median":{"confidence_interval":{"confidence_level":0.95,"lower_bound":79064.43162393162,"upper_bound":79284.0113173559},"point_estimate":79157.76506660169,"standard_error":59.112745124336286},"median_abs_dev":{"confidence_interval":{"confidence_level":0.95,"lower_bound":451.79209796867144,"upper_bound":1461.1752571662466},"point_estimate":660.9312506079684,"standard_error":242.6831610707957},"slope":{"confidence_interval":{"confidence_level":0.95,"lower_bound":79852.24323024089,"upper_bound":80885.15884620049},"point_estimate":80341.42327077485,"standard_error":265.368196442658},"std_dev":{"confidence_interval":{"confidence_level":0.95,"lower_bound":2254.4308175878396,"upper_bound":6755.775258377668},"point_estimate":4541.304460408394,"standard_error":1224.1457367612063}}