{"mean":{"confidence_interval":{"confidence_level":0.95,"lower_bound":80933.77163680836,"upper_bound":82620.46658162297},"point_estimate":81857.77609181315,"standard_error":431.1273106719486},"median":{"confidence_interval":{"confidence_level":0.95,"lower_bound":81766.77316750279,"upper_bound":82312.26107416101},"point_estimate":82048.64152489809,"standard_error":124.36502716169124},"median_abs_dev":{"confidence_interval":{"confidence_level":0.95,"lower_bound":916.3413956531525,"upper_bound":2268.884588260899},"point_estimate":1263.2529949177351,"standard_error":360.63548201768924},"slope":{"confidence_interval":{"confidence_level":0.95,"lower_bound":82706.48883474193,"upper_bound":83682.66014830607},"point_estimate":83174.22989261613,"standard_error":249.7112691611195},"std_dev":{"confidence_interval":{"confidence_level":0.95,"lower_bound":2401.942096742479,"upper_bound":6296.555936260582},"point_estimate":4321.771550493586,"standard_error":1077.5906513186687}}