{"mean":{"confidence_interval":{"confidence_level":0.95,"lower_bound":694843.592439148,"upper_bound":704875.0105774774},"point_estimate":699555.2961933922,"standard_error":2552.785422076401},"median":{"confidence_interval":{"confidence_level":0.95,"lower_bound":693154.9969945354,"upper_bound":699545.1634615385},"point_estimate":695364.4628378379,"standard_error":1779.7959257422974},"median_abs_dev":{"confidence_interval":{"confidence_level":0.95,"lower_bound":9432.288672729448,"upper_bound":19620.329322124097},"point_estimate":13894.30144117642,"standard_error":2635.7215479572956},"slope":{"confidence_interval":{"confidence_level":0.95,"lower_bound":694563.7306272765,"upper_bound":703671.3500158649},"point_estimate":698989.4227294222,"standard_error":2306.99657837049},"std_dev":{"confidence_interval":{"confidence_level":0.95,"lower_bound":16534.0363400352,"upper_bound":34323.49802962275},"point_estimate":25648.283434926932,"standard_error":4640.293615691678}}