{"mean":{"confidence_interval":{"confidence_level":0.95,"lower_bound":584445.4605084104,"upper_bound":584817.5404095154},"point_estimate":584636.1643206904,"standard_error":95.0099021462706},"median":{"confidence_interval":{"confidence_level":0.95,"lower_bound":584430.9107142857,"upper_bound":584836.1014492754},"point_estimate":584719.4232954546,"standard_error":92.86558649754062},"median_abs_dev":{"confidence_interval":{"confidence_level":0.95,"lower_bound":572.252951433185,"upper_bound":944.6085880612922},"point_estimate":710.3640995015016,"standard_error":99.8923058032745},"slope":{"confidence_interval":{"confidence_level":0.95,"lower_bound":584588.1044904753,"upper_bound":584884.0320684938},"point_estimate":584732.6163425447,"standard_error":75.29151430218124},"std_dev":{"confidence_interval":{"confidence_level":0.95,"lower_bound":727.7926152821329,"upper_bound":1179.292027936786},"point_estimate":952.1998317004095,"standard_error":116.97315181934226}}