{"mean":{"confidence_interval":{"confidence_level":0.95,"lower_bound":127600.7265490062,"upper_bound":127943.52381494951},"point_estimate":127766.69111891501,"standard_error":87.69488039860886},"median":{"confidence_interval":{"confidence_level":0.95,"lower_bound":127433.65446466923,"upper_bound":127771.0},"point_estimate":127630.58302645935,"standard_error":93.63554885950832},"median_abs_dev":{"confidence_interval":{"confidence_level":0.95,"lower_bound":522.1537674913797,"upper_bound":956.454285292266},"point_estimate":710.2734394515318,"standard_error":112.00872980563472},"slope":{"confidence_interval":{"confidence_level":0.95,"lower_bound":127405.94178368905,"upper_bound":127704.31436808956},"point_estimate":127547.00810403428,"standard_error":76.41215342983163},"std_dev":{"confidence_interval":{"confidence_level":0.95,"lower_bound":696.8493370593914,"upper_bound":1079.189923346135},"point_estimate":884.9799813780372,"standard_error":99.24724277342274}}