{"mean":{"confidence_interval":{"confidence_level":0.95,"lower_bound":9518.080021135826,"upper_bound":9664.020152213803},"point_estimate":9578.50402035166,"standard_error":38.15854000384184},"median":{"confidence_interval":{"confidence_level":0.95,"lower_bound":9499.040229885057,"upper_bound":9527.881465026203},"point_estimate":9510.806169636815,"standard_error":7.05740339789375},"median_abs_dev":{"confidence_interval":{"confidence_level":0.95,"lower_bound":40.16979691851801,"upper_bound":66.61523707640626},"point_estimate":52.75431207777898,"standard_error":6.7742508801304595},"slope":{"confidence_interval":{"confidence_level":0.95,"lower_bound":9512.57765562405,"upper_bound":9556.873502704275},"point_estimate":9532.139601810928,"standard_error":11.369582395674835},"std_dev":{"confidence_interval":{"confidence_level":0.95,"lower_bound":79.2626669165926,"upper_bound":601.6713365582589},"point_estimate":382.88604235590316,"standard_error":140.79787631565242}}