{"mean":{"confidence_interval":{"confidence_level":0.95,"lower_bound":19522457.542916663,"upper_bound":19526358.31508333},"point_estimate":19524152.959999993,"standard_error":999.2281744268075},"median":{"confidence_interval":{"confidence_level":0.95,"lower_bound":19521767.833333336,"upper_bound":19523199.0},"point_estimate":19522465.333333332,"standard_error":367.2491960021334},"median_abs_dev":{"confidence_interval":{"confidence_level":0.95,"lower_bound":3311.634141205821,"upper_bound":5858.740895988398},"point_estimate":4532.802319524832,"standard_error":642.2026801229692},"slope":null,"std_dev":{"confidence_interval":{"confidence_level":0.95,"lower_bound":5101.3397904041785,"upper_bound":15108.32952473462},"point_estimate":9991.937242782456,"standard_error":3013.881819933651}}