{"mean":{"confidence_interval":{"confidence_level":0.95,"lower_bound":21174389.931333333,"upper_bound":21562909.438750003},"point_estimate":21365829.64666667,"standard_error":99226.10284407792},"median":{"confidence_interval":{"confidence_level":0.95,"lower_bound":21036538.0,"upper_bound":21448472.666666668},"point_estimate":21267722.0,"standard_error":103397.01825258113},"median_abs_dev":{"confidence_interval":{"confidence_level":0.95,"lower_bound":834476.7002850752,"upper_bound":1380482.4410915365},"point_estimate":1114750.3645092258,"standard_error":140172.4411836901},"slope":null,"std_dev":{"confidence_interval":{"confidence_level":0.95,"lower_bound":860279.1316511619,"upper_bound":1119800.9218682211},"point_estimate":993087.0669437093,"standard_error":66269.37502805337}}