{"mean":{"confidence_interval":{"confidence_level":0.95,"lower_bound":6860958.73015625,"upper_bound":7040444.2445625},"point_estimate":6929122.85125,"standard_error":48438.761440138594},"median":{"confidence_interval":{"confidence_level":0.95,"lower_bound":6824551.375,"upper_bound":6826654.125},"point_estimate":6825469.375,"standard_error":550.0889032119187},"median_abs_dev":{"confidence_interval":{"confidence_level":0.95,"lower_bound":3981.800216808915,"upper_bound":8018.271307647228},"point_estimate":5493.866864964366,"standard_error":1031.1375763545434},"slope":null,"std_dev":{"confidence_interval":{"confidence_level":0.95,"lower_bound":105189.02498152215,"upper_bound":811556.7179443442},"point_estimate":487518.71991833067,"standard_error":231880.21450500132}}