{"mean":{"confidence_interval":{"confidence_level":0.95,"lower_bound":6873458.718785714,"upper_bound":6964034.226821429},"point_estimate":6914705.618571428,"standard_error":23196.4231515113},"median":{"confidence_interval":{"confidence_level":0.95,"lower_bound":6825229.857142857,"upper_bound":6829140.142857143},"point_estimate":6827058.857142857,"standard_error":1252.0459362188049},"median_abs_dev":{"confidence_interval":{"confidence_level":0.95,"lower_bound":4654.304917369175,"upper_bound":11527.32069534974},"point_estimate":7558.4005658114675,"standard_error":1990.923190539894},"slope":null,"std_dev":{"confidence_interval":{"confidence_level":0.95,"lower_bound":132454.99405197942,"upper_bound":310743.6214683522},"point_estimate":232961.48250896033,"standard_error":46627.65404631022}}