{"mean":{"confidence_interval":{"confidence_level":0.95,"lower_bound":6855465.930607148,"upper_bound":6903623.063142858},"point_estimate":6877884.982857145,"standard_error":12354.021575266559},"median":{"confidence_interval":{"confidence_level":0.95,"lower_bound":6830448.857142857,"upper_bound":6837686.428571428},"point_estimate":6832801.714285715,"standard_error":2064.9992350983525},"median_abs_dev":{"confidence_interval":{"confidence_level":0.95,"lower_bound":9948.775323374128,"upper_bound":18091.637978810402},"point_estimate":13410.752161911654,"standard_error":2113.3376147588324},"slope":null,"std_dev":{"confidence_interval":{"confidence_level":0.95,"lower_bound":79408.64134946695,"upper_bound":163326.71960419093},"point_estimate":124693.40994609814,"standard_error":21406.129784562545}}