{"mean":{"confidence_interval":{"confidence_level":0.95,"lower_bound":152359665.00175,"upper_bound":153917748.48575},"point_estimate":153121013.4,"standard_error":398006.804147926},"median":{"confidence_interval":{"confidence_level":0.95,"lower_bound":151378541.0,"upper_bound":153141958.0},"point_estimate":152536261.0,"standard_error":471254.952035008},"median_abs_dev":{"confidence_interval":{"confidence_level":0.95,"lower_bound":2949514.0396356583,"upper_bound":5249130.9367842935},"point_estimate":4173489.273905754,"standard_error":596728.4684096848},"slope":null,"std_dev":{"confidence_interval":{"confidence_level":0.95,"lower_bound":3430284.0635478566,"upper_bound":4495416.764903864},"point_estimate":3998967.199958977,"standard_error":270824.8931084585}}