{"mean":{"confidence_interval":{"confidence_level":0.95,"lower_bound":52684.743107512004,"upper_bound":55449.43504699073},"point_estimate":53960.064164776195,"standard_error":707.8059196073389},"median":{"confidence_interval":{"confidence_level":0.95,"lower_bound":51592.76485507247,"upper_bound":52939.17424242424},"point_estimate":52281.677849264706,"standard_error":387.65838376183115},"median_abs_dev":{"confidence_interval":{"confidence_level":0.95,"lower_bound":1871.2379846174133,"upper_bound":3366.138844199292},"point_estimate":2577.754837176882,"standard_error":393.51224866915277},"slope":{"confidence_interval":{"confidence_level":0.95,"lower_bound":53171.34431779592,"upper_bound":55828.97408420726},"point_estimate":54369.83415693808,"standard_error":679.2825040586977},"std_dev":{"confidence_interval":{"confidence_level":0.95,"lower_bound":4236.604743609592,"upper_bound":9416.379858140017},"point_estimate":7103.772388325929,"standard_error":1321.3875186754099}}