{"mean":{"confidence_interval":{"confidence_level":0.95,"lower_bound":50392.04486025774,"upper_bound":52164.53457613562},"point_estimate":51181.313476746494,"standard_error":453.7747488890374},"median":{"confidence_interval":{"confidence_level":0.95,"lower_bound":49634.96388888889,"upper_bound":50302.532051282054},"point_estimate":49987.747697368424,"standard_error":161.0302650305762},"median_abs_dev":{"confidence_interval":{"confidence_level":0.95,"lower_bound":827.4455514003326,"upper_bound":1439.806570652325},"point_estimate":1035.2231031175736,"standard_error":160.86012006442408},"slope":{"confidence_interval":{"confidence_level":0.95,"lower_bound":49896.450203879,"upper_bound":51961.504536814995},"point_estimate":50806.017233633815,"standard_error":533.2524750244906},"std_dev":{"confidence_interval":{"confidence_level":0.95,"lower_bound":2315.98572501494,"upper_bound":6748.298897143938},"point_estimate":4584.935764883257,"standard_error":1219.7268262181908}}