{"mean":{"confidence_interval":{"confidence_level":0.95,"lower_bound":75813.19674250427,"upper_bound":76984.92108687345},"point_estimate":76459.67968071582,"standard_error":299.2032130812995},"median":{"confidence_interval":{"confidence_level":0.95,"lower_bound":76846.55210918114,"upper_bound":77074.42562997347},"point_estimate":76962.83977481678,"standard_error":59.20063961522557},"median_abs_dev":{"confidence_interval":{"confidence_level":0.95,"lower_bound":337.94383432048227,"upper_bound":660.6604739065658},"point_estimate":500.07193761919837,"standard_error":84.69187691560857},"slope":{"confidence_interval":{"confidence_level":0.95,"lower_bound":77149.41560447993,"upper_bound":77578.37106106819},"point_estimate":77339.78250809926,"standard_error":110.3359263778369},"std_dev":{"confidence_interval":{"confidence_level":0.95,"lower_bound":1307.281770037996,"upper_bound":4526.781206853972},"point_estimate":3008.0609167214484,"standard_error":852.9908319910636}}