{"mean":{"confidence_interval":{"confidence_level":0.95,"lower_bound":173557.99206016597,"upper_bound":173746.86064490146},"point_estimate":173652.05769832648,"standard_error":48.066476721028934},"median":{"confidence_interval":{"confidence_level":0.95,"lower_bound":173543.30888030888,"upper_bound":173724.136},"point_estimate":173631.3094771242,"standard_error":44.318774775701655},"median_abs_dev":{"confidence_interval":{"confidence_level":0.95,"lower_bound":300.1413653960626,"upper_bound":497.9774391873249},"point_estimate":399.38772290944763,"standard_error":50.180033665367496},"slope":{"confidence_interval":{"confidence_level":0.95,"lower_bound":173548.77002448906,"upper_bound":173753.59444900847},"point_estimate":173645.80422461947,"standard_error":52.24621296108475},"std_dev":{"confidence_interval":{"confidence_level":0.95,"lower_bound":374.4409258585676,"upper_bound":584.9237347238954},"point_estimate":482.8605842587165,"standard_error":53.71326008377752}}