{"mean":{"confidence_interval":{"confidence_level":0.95,"lower_bound":178666.98880316474,"upper_bound":179026.59613437098},"point_estimate":178832.45484035782,"standard_error":91.6950963451694},"median":{"confidence_interval":{"confidence_level":0.95,"lower_bound":178741.53430777718,"upper_bound":178922.225},"point_estimate":178836.42694736843,"standard_error":45.68682541700914},"median_abs_dev":{"confidence_interval":{"confidence_level":0.95,"lower_bound":314.30682311696233,"upper_bound":498.1159244521383},"point_estimate":411.36019288921204,"standard_error":45.48107447360902},"slope":{"confidence_interval":{"confidence_level":0.95,"lower_bound":178781.16277800148,"upper_bound":179077.90915824892},"point_estimate":178914.2707220334,"standard_error":75.82099866749337},"std_dev":{"confidence_interval":{"confidence_level":0.95,"lower_bound":499.6623886129687,"upper_bound":1363.79606164851},"point_estimate":922.7088893705843,"standard_error":242.68785293661315}}