{"mean":{"confidence_interval":{"confidence_level":0.95,"lower_bound":241376.77925019898,"upper_bound":241741.1396768368},"point_estimate":241550.14671867984,"standard_error":93.01826101159942},"median":{"confidence_interval":{"confidence_level":0.95,"lower_bound":241162.8625,"upper_bound":241529.71875},"point_estimate":241353.5438218391,"standard_error":100.9542608293676},"median_abs_dev":{"confidence_interval":{"confidence_level":0.95,"lower_bound":490.9051007955409,"upper_bound":820.3203826490987},"point_estimate":606.0662203478631,"standard_error":88.65316760300621},"slope":{"confidence_interval":{"confidence_level":0.95,"lower_bound":241343.4527962436,"upper_bound":241922.35794694087},"point_estimate":241614.356826511,"standard_error":148.0934447422175},"std_dev":{"confidence_interval":{"confidence_level":0.95,"lower_bound":715.5534198714597,"upper_bound":1127.3503813281231},"point_estimate":935.8546319681479,"standard_error":105.44485768912503}}