{"mean":{"confidence_interval":{"confidence_level":0.95,"lower_bound":77172.7668076188,"upper_bound":78764.63159357497},"point_estimate":78055.57488714062,"standard_error":406.78226766989934},"median":{"confidence_interval":{"confidence_level":0.95,"lower_bound":78173.60746606335,"upper_bound":78430.96195202647},"point_estimate":78344.01191981402,"standard_error":75.88573130830807},"median_abs_dev":{"confidence_interval":{"confidence_level":0.95,"lower_bound":461.0569852430836,"upper_bound":1111.2780163433513},"point_estimate":662.7151652284643,"standard_error":165.27550429379454},"slope":{"confidence_interval":{"confidence_level":0.95,"lower_bound":78563.55205224184,"upper_bound":79114.4473488404},"point_estimate":78804.65706107694,"standard_error":141.37561897395034},"std_dev":{"confidence_interval":{"confidence_level":0.95,"lower_bound":2053.2622455257574,"upper_bound":6094.510116090278},"point_estimate":4093.514435512274,"standard_error":1116.183599748671}}