{"mean":{"confidence_interval":{"confidence_level":0.95,"lower_bound":78089.99558743284,"upper_bound":79778.78822710805},"point_estimate":79010.98131531585,"standard_error":432.03815649222867},"median":{"confidence_interval":{"confidence_level":0.95,"lower_bound":78576.89156505595,"upper_bound":79072.24015009381},"point_estimate":78791.18614370564,"standard_error":121.21729003893996},"median_abs_dev":{"confidence_interval":{"confidence_level":0.95,"lower_bound":820.818666196789,"upper_bound":2018.9365620588133},"point_estimate":1338.0201951776194,"standard_error":329.8664200472606},"slope":{"confidence_interval":{"confidence_level":0.95,"lower_bound":79599.42059456419,"upper_bound":80828.36857718417},"point_estimate":80187.1454927192,"standard_error":313.808595281524},"std_dev":{"confidence_interval":{"confidence_level":0.95,"lower_bound":2441.4678225985585,"upper_bound":6298.766930617244},"point_estimate":4340.196903773378,"standard_error":1067.8982743000008}}