{"mean":{"confidence_interval":{"confidence_level":0.95,"lower_bound":43336238.903749995,"upper_bound":43502675.326749995},"point_estimate":43416158.255,"standard_error":42498.90525135545},"median":{"confidence_interval":{"confidence_level":0.95,"lower_bound":43261895.5,"upper_bound":43411340.0},"point_estimate":43311661.25,"standard_error":42514.956513114215},"median_abs_dev":{"confidence_interval":{"confidence_level":0.95,"lower_bound":248818.08188259602,"upper_bound":430050.7320150733},"point_estimate":320880.59490323067,"standard_error":44696.41469807657},"slope":null,"std_dev":{"confidence_interval":{"confidence_level":0.95,"lower_bound":320483.89767125755,"upper_bound":543552.8476313686},"point_estimate":425548.3645837824,"standard_error":59669.313463011014}}