{"mean":{"confidence_interval":{"confidence_level":0.95,"lower_bound":43560753.095,"upper_bound":43884184.27},"point_estimate":43720296.255,"standard_error":82677.6201680178},"median":{"confidence_interval":{"confidence_level":0.95,"lower_bound":43175030.5,"upper_bound":43598583.0},"point_estimate":43338825.25,"standard_error":93934.25195995353},"median_abs_dev":{"confidence_interval":{"confidence_level":0.95,"lower_bound":379309.48921591043,"upper_bound":986707.5420736893},"point_estimate":630097.5758135319,"standard_error":145749.33424378344},"slope":null,"std_dev":{"confidence_interval":{"confidence_level":0.95,"lower_bound":746562.1106523945,"upper_bound":887144.7813523416},"point_estimate":827413.8423363031,"standard_error":35868.77297491301}}