{"mean":{"confidence_interval":{"confidence_level":0.95,"lower_bound":82911812.52325,"upper_bound":83184779.5905},"point_estimate":83046446.58,"standard_error":69779.95208208205},"median":{"confidence_interval":{"confidence_level":0.95,"lower_bound":82825000.0,"upper_bound":83153957.0},"point_estimate":82972403.0,"standard_error":81217.66869282305},"median_abs_dev":{"confidence_interval":{"confidence_level":0.95,"lower_bound":495865.9393966198,"upper_bound":873714.6969884634},"point_estimate":661032.0242643356,"standard_error":99749.87652960564},"slope":null,"std_dev":{"confidence_interval":{"confidence_level":0.95,"lower_bound":606884.6121866843,"upper_bound":783669.8473228036},"point_estimate":699865.2684009132,"standard_error":45076.29427732655}}