{"mean":{"confidence_interval":{"confidence_level":0.95,"lower_bound":8596083.223000003,"upper_bound":8632599.528666664},"point_estimate":8613919.691666666,"standard_error":9338.891653548002},"median":{"confidence_interval":{"confidence_level":0.95,"lower_bound":8593282.0,"upper_bound":8629565.5},"point_estimate":8612840.333333334,"standard_error":8431.569218321449},"median_abs_dev":{"confidence_interval":{"confidence_level":0.95,"lower_bound":52953.89970987943,"upper_bound":111331.95010971448},"point_estimate":87869.1290900102,"standard_error":14698.278496978957},"slope":null,"std_dev":{"confidence_interval":{"confidence_level":0.95,"lower_bound":76726.43379726399,"upper_bound":109763.20291605852},"point_estimate":93648.51425019518,"standard_error":8469.64241938413}}