{"mean":{"confidence_interval":{"confidence_level":0.95,"lower_bound":4421819.930916667,"upper_bound":4451573.067833332},"point_estimate":4438071.194166668,"standard_error":7622.100017938043},"median":{"confidence_interval":{"confidence_level":0.95,"lower_bound":4446373.833333333,"upper_bound":4456346.5},"point_estimate":4451943.958333334,"standard_error":2499.748918438339},"median_abs_dev":{"confidence_interval":{"confidence_level":0.95,"lower_bound":12344.12738084793,"upper_bound":19688.495225458875},"point_estimate":16286.79313585139,"standard_error":1929.5735001078117},"slope":null,"std_dev":{"confidence_interval":{"confidence_level":0.95,"lower_bound":36232.5704954414,"upper_bound":105943.78266384629},"point_estimate":76665.25507852888,"standard_error":17285.29980832095}}