{"mean":{"confidence_interval":{"confidence_level":0.95,"lower_bound":647778.4173112501,"upper_bound":656417.7823949181},"point_estimate":652041.3728025449,"standard_error":2200.7823522266126},"median":{"confidence_interval":{"confidence_level":0.95,"lower_bound":646703.5236111111,"upper_bound":653553.3541666666},"point_estimate":650435.0675025764,"standard_error":1719.0646960221395},"median_abs_dev":{"confidence_interval":{"confidence_level":0.95,"lower_bound":11779.847630213155,"upper_bound":19969.63104559938},"point_estimate":14473.940718784506,"standard_error":2137.887821512125},"slope":{"confidence_interval":{"confidence_level":0.95,"lower_bound":648869.4665903923,"upper_bound":658066.8114005993},"point_estimate":653145.1130323629,"standard_error":2349.872790620764},"std_dev":{"confidence_interval":{"confidence_level":0.95,"lower_bound":16704.52654054916,"upper_bound":27018.738805616118},"point_estimate":22079.44521940086,"standard_error":2634.846105513424}}