{"mean":{"confidence_interval":{"confidence_level":0.95,"lower_bound":75777.41803364451,"upper_bound":77347.61448304474},"point_estimate":76576.01396494186,"standard_error":397.8567413571597},"median":{"confidence_interval":{"confidence_level":0.95,"lower_bound":76509.57437279701,"upper_bound":76762.12698412698},"point_estimate":76644.0595444268,"standard_error":69.67746452655061},"median_abs_dev":{"confidence_interval":{"confidence_level":0.95,"lower_bound":363.1176034085429,"upper_bound":681.1724497572949},"point_estimate":488.0886963927739,"standard_error":81.28446168137329},"slope":{"confidence_interval":{"confidence_level":0.95,"lower_bound":77191.13808148987,"upper_bound":78947.50167546449},"point_estimate":77955.90374896272,"standard_error":453.3586943426129},"std_dev":{"confidence_interval":{"confidence_level":0.95,"lower_bound":2056.0426803436967,"upper_bound":5648.316603045408},"point_estimate":4000.2299554487927,"standard_error":918.600295573048}}