{"mean":{"confidence_interval":{"confidence_level":0.95,"lower_bound":152669154.1095,"upper_bound":152777249.60924998},"point_estimate":152722883.68,"standard_error":27511.62989350508},"median":{"confidence_interval":{"confidence_level":0.95,"lower_bound":152628105.0,"upper_bound":152777460.0},"point_estimate":152698259.5,"standard_error":38479.734908911036},"median_abs_dev":{"confidence_interval":{"confidence_level":0.95,"lower_bound":210234.90016758442,"upper_bound":348649.69241023064},"point_estimate":305566.0784751177,"standard_error":36200.00410534652},"slope":null,"std_dev":{"confidence_interval":{"confidence_level":0.95,"lower_bound":234726.04410144754,"upper_bound":316579.53404080536},"point_estimate":276273.6771124786,"standard_error":21054.18022436968}}