{"mean":{"confidence_interval":{"confidence_level":0.95,"lower_bound":145688985.35225,"upper_bound":145936577.2075},"point_estimate":145811369.59,"standard_error":63168.721850100526},"median":{"confidence_interval":{"confidence_level":0.95,"lower_bound":145595692.0,"upper_bound":145915598.0},"point_estimate":145755796.5,"standard_error":86810.4057382338},"median_abs_dev":{"confidence_interval":{"confidence_level":0.95,"lower_bound":528111.7475241423,"upper_bound":879715.5203819275},"point_estimate":733975.2016693354,"standard_error":90515.1012781636},"slope":null,"std_dev":{"confidence_interval":{"confidence_level":0.95,"lower_bound":534173.6993354913,"upper_bound":755899.6761688534},"point_estimate":637866.6398106387,"standard_error":57993.37015894748}}