{"mean":{"confidence_interval":{"confidence_level":0.95,"lower_bound":140025343.25425002,"upper_bound":140640732.18325},"point_estimate":140314996.55,"standard_error":157258.64402242625},"median":{"confidence_interval":{"confidence_level":0.95,"lower_bound":140298017.0,"upper_bound":140598324.0},"point_estimate":140469871.0,"standard_error":78146.7687037018},"median_abs_dev":{"confidence_interval":{"confidence_level":0.95,"lower_bound":521589.79023993015,"upper_bound":1367137.7008109519},"point_estimate":853105.8160543442,"standard_error":235308.08181093994},"slope":null,"std_dev":{"confidence_interval":{"confidence_level":0.95,"lower_bound":1019746.7416361466,"upper_bound":2172817.7470574575},"point_estimate":1585306.3036098224,"standard_error":307926.3292749285}}