{"mean":{"confidence_interval":{"confidence_level":0.95,"lower_bound":6490340.9506250005,"upper_bound":6503230.446312499},"point_estimate":6496755.73,"standard_error":3297.224420353054},"median":{"confidence_interval":{"confidence_level":0.95,"lower_bound":6490236.0,"upper_bound":6498004.875},"point_estimate":6494071.3125,"standard_error":1967.4942488791103},"median_abs_dev":{"confidence_interval":{"confidence_level":0.95,"lower_bound":18334.109262004495,"upper_bound":34759.64904539287},"point_estimate":24086.689822375774,"standard_error":4058.6558626861447},"slope":null,"std_dev":{"confidence_interval":{"confidence_level":0.95,"lower_bound":27248.716915140794,"upper_bound":38271.36029335095},"point_estimate":33052.2794376839,"standard_error":2812.7232027982473}}