{"mean":{"confidence_interval":{"confidence_level":0.95,"lower_bound":17981312.79575,"upper_bound":17987711.349249993},"point_estimate":17984060.083333336,"standard_error":1653.518848317368},"median":{"confidence_interval":{"confidence_level":0.95,"lower_bound":17979302.666666668,"upper_bound":17982504.5},"point_estimate":17981004.333333332,"standard_error":819.9781774948564},"median_abs_dev":{"confidence_interval":{"confidence_level":0.95,"lower_bound":4643.997317550726,"upper_bound":7957.855358719826},"point_estimate":6028.251492977142,"standard_error":823.6753339257104},"slope":null,"std_dev":{"confidence_interval":{"confidence_level":0.95,"lower_bound":7565.990574915322,"upper_bound":25514.13494252908},"point_estimate":16566.815652940317,"standard_error":5436.421329852044}}