{"mean":{"confidence_interval":{"confidence_level":0.95,"lower_bound":6963156.8598437505,"upper_bound":6973346.60021875},"point_estimate":6967767.38125,"standard_error":2608.674391746995},"median":{"confidence_interval":{"confidence_level":0.95,"lower_bound":6960415.75,"upper_bound":6966795.0625},"point_estimate":6964506.4375,"standard_error":1677.1896453318002},"median_abs_dev":{"confidence_interval":{"confidence_level":0.95,"lower_bound":11239.38654296101,"upper_bound":17146.732008084655},"point_estimate":15147.909256070852,"standard_error":1507.8744588985246},"slope":null,"std_dev":{"confidence_interval":{"confidence_level":0.95,"lower_bound":12732.871852011927,"upper_bound":37190.055941935774},"point_estimate":26187.754867394655,"standard_error":6364.369339285109}}