{"mean":{"confidence_interval":{"confidence_level":0.95,"lower_bound":19792003.383166667,"upper_bound":20134677.65066666},"point_estimate":19953416.45666666,"standard_error":87730.70074074459},"median":{"confidence_interval":{"confidence_level":0.95,"lower_bound":19503788.0,"upper_bound":19774739.333333332},"point_estimate":19646172.0,"standard_error":70882.69667811172},"median_abs_dev":{"confidence_interval":{"confidence_level":0.95,"lower_bound":256886.14383935745,"upper_bound":609676.8615260683},"point_estimate":431981.9420307884,"standard_error":86529.13704971943},"slope":null,"std_dev":{"confidence_interval":{"confidence_level":0.95,"lower_bound":601352.3486371998,"upper_bound":1148762.436493342},"point_estimate":882886.5865813257,"standard_error":141436.38545132088}}