{"mean":{"confidence_interval":{"confidence_level":0.95,"lower_bound":15742169.694875,"upper_bound":16163301.9938125},"point_estimate":15948493.8525,"standard_error":107256.61722301172},"median":{"confidence_interval":{"confidence_level":0.95,"lower_bound":15392750.5,"upper_bound":15959931.25},"point_estimate":15626585.375,"standard_error":132949.05815174864},"median_abs_dev":{"confidence_interval":{"confidence_level":0.95,"lower_bound":661548.4138351679,"upper_bound":1241751.4040970022},"point_estimate":910483.1763356924,"standard_error":147186.5858511379},"slope":null,"std_dev":{"confidence_interval":{"confidence_level":0.95,"lower_bound":911054.6601134461,"upper_bound":1234115.3920230963},"point_estimate":1081256.309169265,"standard_error":82152.05094365306}}