{"mean":{"confidence_interval":{"confidence_level":0.95,"lower_bound":14976028.5161875,"upper_bound":15025182.908875},"point_estimate":14993316.155,"standard_error":14886.896439392469},"median":{"confidence_interval":{"confidence_level":0.95,"lower_bound":14973582.5,"upper_bound":14976370.125},"point_estimate":14975445.0,"standard_error":690.3096230387974},"median_abs_dev":{"confidence_interval":{"confidence_level":0.95,"lower_bound":4262.840941194445,"upper_bound":7301.80487036705},"point_estimate":5819.390221685171,"standard_error":772.4901290051938},"slope":null,"std_dev":{"confidence_interval":{"confidence_level":0.95,"lower_bound":11191.599486245097,"upper_bound":256456.5880252478},"point_estimate":150113.335243026,"standard_error":86604.12360288695}}