{"mean":{"confidence_interval":{"confidence_level":0.95,"lower_bound":17944722.249666672,"upper_bound":18248121.027833335},"point_estimate":18090457.886666667,"standard_error":77491.18245299002},"median":{"confidence_interval":{"confidence_level":0.95,"lower_bound":17800888.333333336,"upper_bound":18075059.666666668},"point_estimate":17948907.5,"standard_error":70079.98589423906},"median_abs_dev":{"confidence_interval":{"confidence_level":0.95,"lower_bound":417210.55139303394,"upper_bound":693917.3271805029},"point_estimate":594581.3992440691,"standard_error":72420.27948363408},"slope":null,"std_dev":{"confidence_interval":{"confidence_level":0.95,"lower_bound":596539.54545894,"upper_bound":926829.2290425295},"point_estimate":774341.9739367755,"standard_error":84836.49031622581}}