{"mean":{"confidence_interval":{"confidence_level":0.95,"lower_bound":15175454.2531875,"upper_bound":15233695.440437501},"point_estimate":15200471.8025,"standard_error":14981.532753558422},"median":{"confidence_interval":{"confidence_level":0.95,"lower_bound":15170608.25,"upper_bound":15192583.25},"point_estimate":15181658.375,"standard_error":5103.304301527285},"median_abs_dev":{"confidence_interval":{"confidence_level":0.95,"lower_bound":31968.747257441282,"upper_bound":64900.81384778023},"point_estimate":45274.7113712132,"standard_error":8889.08936904573},"slope":null,"std_dev":{"confidence_interval":{"confidence_level":0.95,"lower_bound":73139.26904789657,"upper_bound":231228.11576635105},"point_estimate":150352.1655215365,"standard_error":48841.29826983372}}