{"mean":{"confidence_interval":{"confidence_level":0.95,"lower_bound":44759009.37,"upper_bound":44856147.819625},"point_estimate":44807220.965,"standard_error":24755.929518901965},"median":{"confidence_interval":{"confidence_level":0.95,"lower_bound":44762358.5,"upper_bound":44844195.5},"point_estimate":44812724.25,"standard_error":22554.0258319208},"median_abs_dev":{"confidence_interval":{"confidence_level":0.95,"lower_bound":141542.3368871212,"upper_bound":262532.5022891164},"point_estimate":217042.9992467165,"standard_error":32138.199690766556},"slope":null,"std_dev":{"confidence_interval":{"confidence_level":0.95,"lower_bound":202030.48676998424,"upper_bound":289958.2352838777},"point_estimate":247504.95531905242,"standard_error":22619.31729346011}}