{"mean":{"confidence_interval":{"confidence_level":0.95,"lower_bound":14717595.4945625,"upper_bound":14719667.809249999},"point_estimate":14718518.115,"standard_error":532.4660038911076},"median":{"confidence_interval":{"confidence_level":0.95,"lower_bound":14716754.25,"upper_bound":14718454.25},"point_estimate":14717579.25,"standard_error":424.6628668157627},"median_abs_dev":{"confidence_interval":{"confidence_level":0.95,"lower_bound":2479.46313098073,"upper_bound":4558.994919061661},"point_estimate":3372.9149401187897,"standard_error":556.2643853769727},"slope":null,"std_dev":{"confidence_interval":{"confidence_level":0.95,"lower_bound":3038.0767011032785,"upper_bound":7953.977751733997},"point_estimate":5356.546974891304,"standard_error":1524.5758422032231}}