{"mean":{"confidence_interval":{"confidence_level":0.95,"lower_bound":6493381.72475,"upper_bound":6499222.7325625},"point_estimate":6495901.40625,"standard_error":1500.4898817429346},"median":{"confidence_interval":{"confidence_level":0.95,"lower_bound":6490744.375,"upper_bound":6493410.625},"point_estimate":6491593.5625,"standard_error":620.9103235480833},"median_abs_dev":{"confidence_interval":{"confidence_level":0.95,"lower_bound":2988.3470394462365,"upper_bound":5932.067819684744},"point_estimate":4224.019987508655,"standard_error":728.9463616924031},"slope":null,"std_dev":{"confidence_interval":{"confidence_level":0.95,"lower_bound":5750.955490567996,"upper_bound":22117.342100673108},"point_estimate":14973.809512081274,"standard_error":4421.838691363514}}