{"mean":{"confidence_interval":{"confidence_level":0.95,"lower_bound":17330711.78508333,"upper_bound":17610868.631999988},"point_estimate":17460568.51333333,"standard_error":71403.86211156154},"median":{"confidence_interval":{"confidence_level":0.95,"lower_bound":17229602.666666664,"upper_bound":17337520.0},"point_estimate":17292619.666666664,"standard_error":31026.433177059862},"median_abs_dev":{"confidence_interval":{"confidence_level":0.95,"lower_bound":254045.48228978927,"upper_bound":509968.6774462425},"point_estimate":364598.5145270806,"standard_error":66958.46913342777},"slope":null,"std_dev":{"confidence_interval":{"confidence_level":0.95,"lower_bound":450782.34754159674,"upper_bound":950235.4713176731},"point_estimate":719519.7012463893,"standard_error":126872.48578717207}}