{"mean":{"confidence_interval":{"confidence_level":0.95,"lower_bound":6492647.455,"upper_bound":6503575.37746875},"point_estimate":6497381.4275,"standard_error":2829.2246458920786},"median":{"confidence_interval":{"confidence_level":0.95,"lower_bound":6490455.125,"upper_bound":6491745.625},"point_estimate":6491148.3125,"standard_error":326.3585715779137},"median_abs_dev":{"confidence_interval":{"confidence_level":0.95,"lower_bound":2416.45263209939,"upper_bound":3626.1615481227636},"point_estimate":3060.8276456594467,"standard_error":296.59323440807424},"slope":null,"std_dev":{"confidence_interval":{"confidence_level":0.95,"lower_bound":8478.470131558408,"upper_bound":43021.827787219125},"point_estimate":28287.931861095127,"standard_error":8677.705135758693}}