{"mean":{"confidence_interval":{"confidence_level":0.95,"lower_bound":14677286.8156875,"upper_bound":14681749.38975},"point_estimate":14679470.845,"standard_error":1133.4832654982565},"median":{"confidence_interval":{"confidence_level":0.95,"lower_bound":14677540.25,"upper_bound":14682240.375},"point_estimate":14679902.875,"standard_error":1222.511752651578},"median_abs_dev":{"confidence_interval":{"confidence_level":0.95,"lower_bound":8080.540506541729,"upper_bound":12639.16477560997},"point_estimate":10971.425130218267,"standard_error":1143.057405264559},"slope":null,"std_dev":{"confidence_interval":{"confidence_level":0.95,"lower_bound":8929.289493005112,"upper_bound":13995.038643363445},"point_estimate":11395.600021919456,"standard_error":1317.3229282081686}}