{"mean":{"confidence_interval":{"confidence_level":0.95,"lower_bound":233002.9199648575,"upper_bound":233218.79087584384},"point_estimate":233110.00871357723,"standard_error":54.96103968936883},"median":{"confidence_interval":{"confidence_level":0.95,"lower_bound":233027.24772727274,"upper_bound":233212.18541335454},"point_estimate":233131.3125,"standard_error":40.45521046746924},"median_abs_dev":{"confidence_interval":{"confidence_level":0.95,"lower_bound":323.5602408976537,"upper_bound":578.4072572311982},"point_estimate":417.94517157495784,"standard_error":70.53894596924809},"slope":{"confidence_interval":{"confidence_level":0.95,"lower_bound":233126.1224516343,"upper_bound":233316.42714628496},"point_estimate":233218.8578801537,"standard_error":48.45095163118495},"std_dev":{"confidence_interval":{"confidence_level":0.95,"lower_bound":452.3940687496721,"upper_bound":646.5962674449452},"point_estimate":552.9196784519123,"standard_error":49.56053546224315}}