{"mean":{"confidence_interval":{"confidence_level":0.95,"lower_bound":2615023.842287498,"upper_bound":2617597.5568624977},"point_estimate":2616176.8244999982,"standard_error":660.8964797211408},"median":{"confidence_interval":{"confidence_level":0.95,"lower_bound":2614447.125,"upper_bound":2615262.2},"point_estimate":2614859.725,"standard_error":217.75855310864324},"median_abs_dev":{"confidence_interval":{"confidence_level":0.95,"lower_bound":1071.0672859844783,"upper_bound":1897.7650313077977},"point_estimate":1512.2890381513646,"standard_error":213.6269731504566},"slope":null,"std_dev":{"confidence_interval":{"confidence_level":0.95,"lower_bound":2787.7584696458975,"upper_bound":9560.289514640685},"point_estimate":6648.180979139203,"standard_error":1723.9457614957507}}