{"mean":{"confidence_interval":{"confidence_level":0.95,"lower_bound":82129864.712,"upper_bound":83278744.86},"point_estimate":82705561.38,"standard_error":292053.2772799813},"median":{"confidence_interval":{"confidence_level":0.95,"lower_bound":82035809.0,"upper_bound":83103437.0},"point_estimate":82856232.0,"standard_error":245313.83554734962},"median_abs_dev":{"confidence_interval":{"confidence_level":0.95,"lower_bound":2079198.7219968487,"upper_bound":3538912.763571739},"point_estimate":2823983.782464266,"standard_error":369575.933624747},"slope":null,"std_dev":{"confidence_interval":{"confidence_level":0.95,"lower_bound":2523811.5589678334,"upper_bound":3269844.477344952},"point_estimate":2921360.6289565847,"standard_error":190056.48628203364}}