{"mean":{"confidence_interval":{"confidence_level":0.95,"lower_bound":19080068.165916666,"upper_bound":19192705.43699999},"point_estimate":19136358.433333334,"standard_error":28725.25853176903},"median":{"confidence_interval":{"confidence_level":0.95,"lower_bound":19093118.333333332,"upper_bound":19283313.0},"point_estimate":19190475.166666668,"standard_error":45376.291780106694},"median_abs_dev":{"confidence_interval":{"confidence_level":0.95,"lower_bound":174757.51829743202,"upper_bound":374998.9533424414},"point_estimate":281485.1955026379,"standard_error":48278.459227652726},"slope":null,"std_dev":{"confidence_interval":{"confidence_level":0.95,"lower_bound":242992.25087894584,"upper_bound":340501.23186792724},"point_estimate":288419.6663523216,"standard_error":25343.41325121182}}