{"mean":{"confidence_interval":{"confidence_level":0.95,"lower_bound":19114786.246,"upper_bound":19532914.76441667},"point_estimate":19319922.229999993,"standard_error":106615.63890799826},"median":{"confidence_interval":{"confidence_level":0.95,"lower_bound":18953427.166666664,"upper_bound":19557643.333333332},"point_estimate":19311409.666666664,"standard_error":164304.00167068923},"median_abs_dev":{"confidence_interval":{"confidence_level":0.95,"lower_bound":838412.2619152023,"upper_bound":1330140.7589852829},"point_estimate":1127939.5738750733,"standard_error":129555.38216384884},"slope":null,"std_dev":{"confidence_interval":{"confidence_level":0.95,"lower_bound":882569.4980415693,"upper_bound":1246148.3958827006},"point_estimate":1072232.027046035,"standard_error":92984.04207843747}}