{"mean":{"confidence_interval":{"confidence_level":0.95,"lower_bound":6948606.95221875,"upper_bound":6955253.242625},"point_estimate":6951537.695,"standard_error":1714.1795705446743},"median":{"confidence_interval":{"confidence_level":0.95,"lower_bound":6946745.25,"upper_bound":6948808.75},"point_estimate":6947927.0,"standard_error":560.9346942230709},"median_abs_dev":{"confidence_interval":{"confidence_level":0.95,"lower_bound":4485.79154536128,"upper_bound":7583.776852861047},"point_estimate":6548.1807712465525,"standard_error":801.7813913943695},"slope":null,"std_dev":{"confidence_interval":{"confidence_level":0.95,"lower_bound":7516.572374809596,"upper_bound":25508.921421837007},"point_estimate":17238.01436269114,"standard_error":4678.576105190841}}