{"mean":{"confidence_interval":{"confidence_level":0.95,"lower_bound":6953824.2649375005,"upper_bound":7048628.11790625},"point_estimate":6991493.1575,"standard_error":25674.686946112994},"median":{"confidence_interval":{"confidence_level":0.95,"lower_bound":6950194.375,"upper_bound":6953664.6875},"point_estimate":6951776.375,"standard_error":939.8897075022904},"median_abs_dev":{"confidence_interval":{"confidence_level":0.95,"lower_bound":3905.5389806628227,"upper_bound":6784.933454543352},"point_estimate":5495.349464938045,"standard_error":761.6597312832016},"slope":null,"std_dev":{"confidence_interval":{"confidence_level":0.95,"lower_bound":9492.417796818238,"upper_bound":409415.3994560704},"point_estimate":257962.8997326492,"standard_error":109539.54968026385}}