{"mean":{"confidence_interval":{"confidence_level":0.95,"lower_bound":3987.639078970454,"upper_bound":4015.9616702512362},"point_estimate":4000.286085585557,"standard_error":7.276155045123745},"median":{"confidence_interval":{"confidence_level":0.95,"lower_bound":3975.5279720279723,"upper_bound":3999.3571794871796},"point_estimate":3985.223370544799,"standard_error":5.785989578121893},"median_abs_dev":{"confidence_interval":{"confidence_level":0.95,"lower_bound":32.85476703047881,"upper_bound":59.19967725692539},"point_estimate":45.39048695362011,"standard_error":6.967078721354087},"slope":{"confidence_interval":{"confidence_level":0.95,"lower_bound":4009.702799674355,"upper_bound":4056.280784887881},"point_estimate":4030.351700446738,"standard_error":12.078228508850145},"std_dev":{"confidence_interval":{"confidence_level":0.95,"lower_bound":42.42702180839345,"upper_bound":107.50607868262352},"point_estimate":73.27840865280675,"standard_error":19.855307284351586}}